era5_downloader/__init__.py
era5_downloader/core.py
era5_downloader/defaults.py
era5_downloader/utils.py
era5_downloader-0.1.9.dist-info/METADATA
era5_downloader-0.1.9.dist-info/WHEEL
era5_downloader-0.1.9.dist-info/RECORD
