Metadata-Version: 2.4
Name: era5-downloader
Version: 0.1.9
Summary: A lightweight and fast downloader for ERA5 data from the Google Cloud ARCO store. 
Author-email: Luke Gregor <lukgre@gmail.com>
License-Expression: MIT
Requires-Python: >=3.9
Requires-Dist: dask[array]>=2024
Requires-Dist: fsspec>=2024
Requires-Dist: gcsfs>=2024
Requires-Dist: h5netcdf>=1.1
Requires-Dist: loguru>=0.7
Requires-Dist: netcdf4>=1.6
Requires-Dist: pandas>=2
Requires-Dist: python-dotenv>=1
Requires-Dist: scipy>=1.1
Requires-Dist: tenacity>=9.0.0
Requires-Dist: xarray>=2024
Provides-Extra: full
Requires-Dist: ipykernel; extra == 'full'
Requires-Dist: ipywidgets; extra == 'full'
Requires-Dist: matplotlib; extra == 'full'
Requires-Dist: plotly; extra == 'full'
Requires-Dist: s3fs; extra == 'full'
Requires-Dist: tqdm; extra == 'full'
Requires-Dist: zarr<3; extra == 'full'
Provides-Extra: jupyter
Requires-Dist: ipykernel; extra == 'jupyter'
Requires-Dist: ipywidgets; extra == 'jupyter'
